{
  "as_of_date": "2026-06-09",
  "winner_model": "model_a",
  "final_signal": "XLP",
  "final_confidence": 0.1234,
  "tsl_status": {
    "two_day_cumul_pct": 1.55,
    "tsl_triggered": false,
    "in_cash": false,
    "current_z": 2.809,
    "z_reentry": 0.9,
    "tsl_pct": 12
  },
  "tbill_rate": 3.63,
  "predictions": {
    "model_a": {
      "model": "model_a",
      "lookback": 30,
      "wavelet": "db2",
      "signal": "XLP",
      "confidence": 0.1234,
      "z_score": 2.809,
      "probabilities": {
        "QQQ": 0.0238,
        "XLK": 0.0593,
        "XLF": 0.0476,
        "XLE": 0.0474,
        "XLV": 0.0464,
        "XLI": 0.027,
        "XLY": 0.0722,
        "XLP": 0.1234,
        "XLU": 0.0409,
        "XME": 0.0961,
        "XLB": 0.0506,
        "XLRE": 0.0335,
        "GDX": 0.0577,
        "IWM": 0.0578,
        "IWF": 0.0178,
        "XSD": 0.0578,
        "XBI": 0.059,
        "IWD": 0.0181,
        "IWO": 0.0636
      }
    },
    "model_b": {
      "model": "model_b",
      "lookback": 60,
      "wavelet": "sym5",
      "signal": "XLB",
      "confidence": 0.0974,
      "z_score": 2.288,
      "probabilities": {
        "QQQ": 0.0428,
        "XLK": 0.0657,
        "XLF": 0.0463,
        "XLE": 0.0524,
        "XLV": 0.0573,
        "XLI": 0.0174,
        "XLY": 0.0621,
        "XLP": 0.0393,
        "XLU": 0.0518,
        "XME": 0.0713,
        "XLB": 0.0974,
        "XLRE": 0.0647,
        "GDX": 0.0768,
        "IWM": 0.0551,
        "IWF": 0.032,
        "XSD": 0.0543,
        "XBI": 0.0423,
        "IWD": 0.0107,
        "IWO": 0.0604
      }
    },
    "model_c": {
      "model": "model_c",
      "lookback": 45,
      "wavelet": "sym5",
      "signal": "GDX",
      "confidence": 0.0744,
      "z_score": 2.044,
      "probabilities": {
        "QQQ": 0.0585,
        "XLK": 0.0529,
        "XLF": 0.0523,
        "XLE": 0.0608,
        "XLV": 0.0603,
        "XLI": 0.038,
        "XLY": 0.0582,
        "XLP": 0.0456,
        "XLU": 0.0619,
        "XME": 0.0613,
        "XLB": 0.0548,
        "XLRE": 0.0364,
        "GDX": 0.0744,
        "IWM": 0.0537,
        "IWF": 0.0418,
        "XSD": 0.043,
        "XBI": 0.0599,
        "IWD": 0.0299,
        "IWO": 0.0565
      }
    }
  },
  "trained_from_year": 2025,
  "trained_wavelet": "sym5",
  "trained_at": "2026-05-29T07:26:33.176215",
  "universe": "equity",
  "etfs": [
    "QQQ",
    "XLK",
    "XLF",
    "XLE",
    "XLV",
    "XLI",
    "XLY",
    "XLP",
    "XLU",
    "XME",
    "XLB",
    "XLRE",
    "GDX",
    "IWM",
    "IWF",
    "XSD",
    "XBI",
    "IWD",
    "IWO"
  ]
}