{
  "model_a": {
    "best_lookback": 60,
    "results": [
      {
        "val_mse": 1.8208308219909668,
        "val_acc": 0.2567901313304901,
        "lookback": 30,
        "model": "A"
      },
      {
        "val_mse": 1.9455896615982056,
        "val_acc": 0.08684863895177841,
        "lookback": 45,
        "model": "A"
      },
      {
        "val_mse": 1.7967358827590942,
        "val_acc": 0.21641790866851807,
        "lookback": 60,
        "model": "A"
      }
    ]
  },
  "model_b": {
    "best_lookback": 60,
    "results": [
      {
        "val_mse": 1.8036943674087524,
        "val_acc": 0.2074074000120163,
        "lookback": 30,
        "model": "B"
      },
      {
        "val_mse": 1.9429690837860107,
        "val_acc": 0.08684863895177841,
        "lookback": 45,
        "model": "B"
      },
      {
        "val_mse": 1.7718307971954346,
        "val_acc": 0.2537313401699066,
        "lookback": 60,
        "model": "B"
      }
    ]
  },
  "model_c": {
    "best_lookback": 60,
    "results": [
      {
        "val_mse": 1.8117058277130127,
        "val_acc": 0.19012345373630524,
        "lookback": 30,
        "model": "C"
      },
      {
        "val_mse": 1.8017505407333374,
        "val_acc": 0.23325061798095703,
        "lookback": 45,
        "model": "C"
      },
      {
        "val_mse": 1.7592203617095947,
        "val_acc": 0.25621891021728516,
        "lookback": 60,
        "model": "C"
      }
    ]
  },
  "trained_at": "2026-03-17T04:25:37.595465",
  "epochs": 80,
  "start_year": 2008,
  "wavelet": "db4"
}